<?xml version="1.0" encoding="UTF-8" standalone="yes"?>
<data>
    <planet>
        <id>0</id>
        <positionX>400</positionX>
        <positionY>140</positionY>
        <radius>30</radius>
        <speedUp>1</speedUp>
        <population>10</population>
        <populationMaxConst>100</populationMaxConst>
        <populationSmallMaxConst>10</populationSmallMaxConst>
        <planetType>13</planetType>
        <owner>0</owner>
    </planet>
    <planet>
        <id>0</id>
        <positionX>250</positionX>
        <positionY>300</positionY>
        <radius>40</radius>
        <speedUp>1</speedUp>
        <population>10</population>
        <populationMaxConst>100</populationMaxConst>
        <populationSmallMaxConst>10</populationSmallMaxConst>
        <planetType>7</planetType>
        <owner>0</owner>
    </planet>
    <planet>
        <id>0</id>
        <positionX>233</positionX>
        <positionY>610</positionY>
        <radius>40</radius>
        <speedUp>1</speedUp>
        <population>10</population>
        <populationMaxConst>100</populationMaxConst>
        <populationSmallMaxConst>10</populationSmallMaxConst>
        <planetType>11</planetType>
        <owner>0</owner>
    </planet>
    <planet>
        <id>0</id>
        <positionX>433</positionX>
        <positionY>500</positionY>
        <radius>50</radius>
        <speedUp>1</speedUp>
        <population>10</population>
        <populationMaxConst>100</populationMaxConst>
        <populationSmallMaxConst>10</populationSmallMaxConst>
        <planetType>9</planetType>
        <owner>0</owner>
    </planet>
    <planet>
        <id>0</id>
        <positionX>960</positionX>
        <positionY>300</positionY>
        <radius>30</radius>
        <speedUp>1</speedUp>
        <population>15</population>
        <populationMaxConst>100</populationMaxConst>
        <populationSmallMaxConst>10</populationSmallMaxConst>
        <planetType>0</planetType>
        <owner>0</owner>
    </planet>
    <planet>
        <id>0</id>
        <positionX>866</positionX>
        <positionY>600</positionY>
        <radius>60</radius>
        <speedUp>1</speedUp>
        <population>15</population>
        <populationMaxConst>100</populationMaxConst>
        <populationSmallMaxConst>10</populationSmallMaxConst>
        <planetType>8</planetType>
        <owner>0</owner>
    </planet>
    <planet>
        <id>0</id>
        <positionX>100</positionX>
        <positionY>120</positionY>
        <radius>60</radius>
        <speedUp>1</speedUp>
        <population>30</population>
        <populationMaxConst>100</populationMaxConst>
        <populationSmallMaxConst>20</populationSmallMaxConst>
        <planetType>5</planetType>
        <owner>1</owner>
    </planet>
    <planet>
        <id>0</id>
        <positionX>1200</positionX>
        <positionY>410</positionY>
        <radius>60</radius>
        <speedUp>2</speedUp>
        <population>30</population>
        <populationMaxConst>100</populationMaxConst>
        <populationSmallMaxConst>20</populationSmallMaxConst>
        <planetType>3</planetType>
        <owner>2</owner>
    </planet>
    <bcgIndex>0</bcgIndex>
</data>
